tltorch/__init__.py
tltorch/factorized_layers/__init__.py
tltorch/factorized_layers/factorized_convolution.py
tltorch/factorized_layers/factorized_embedding.py
tltorch/factorized_layers/factorized_linear.py
tltorch/factorized_layers/tensor_contraction_layers.py
tltorch/factorized_layers/tensor_regression_layers.py
tltorch/factorized_layers/tests/__init__.py
tltorch/factorized_layers/tests/test_factorized_convolution.py
tltorch/factorized_layers/tests/test_factorized_embedding.py
tltorch/factorized_layers/tests/test_factorized_linear.py
tltorch/factorized_layers/tests/test_tensor_contraction_layers.py
tltorch/factorized_layers/tests/test_trl.py
tltorch/factorized_tensors/__init__.py
tltorch/factorized_tensors/complex_factorized_tensors.py
tltorch/factorized_tensors/complex_tensorized_matrices.py
tltorch/factorized_tensors/core.py
tltorch/factorized_tensors/factorized_tensors.py
tltorch/factorized_tensors/init.py
tltorch/factorized_tensors/tensorized_matrices.py
tltorch/factorized_tensors/tests/__init__.py
tltorch/factorized_tensors/tests/test_factorizations.py
tltorch/functional/__init__.py
tltorch/functional/convolution.py
tltorch/functional/factorized_linear.py
tltorch/functional/factorized_tensordot.py
tltorch/functional/linear.py
tltorch/functional/tensor_regression.py
tltorch/functional/tests/__init__.py
tltorch/functional/tests/test_factorized_linear.py
tltorch/tensor_hooks/__init__.py
tltorch/tensor_hooks/_tensor_dropout.py
tltorch/tensor_hooks/_tensor_lasso.py
tltorch/tensor_hooks/tests/__init__.py
tltorch/tensor_hooks/tests/test_tensor_dropout.py
tltorch/tensor_hooks/tests/test_tensor_lasso.py
tltorch/utils/__init__.py
tltorch/utils/parameter_list.py
tltorch/utils/tensorize_shape.py
tensorly_torch-0.5.0.dist-info/LICENSE
tensorly_torch-0.5.0.dist-info/METADATA
tensorly_torch-0.5.0.dist-info/WHEEL
tensorly_torch-0.5.0.dist-info/top_level.txt
tensorly_torch-0.5.0.dist-info/RECORD
