Metadata-Version: 2.1
Name: tensorly-torch
Version: 0.5.0
Summary: Deep Learning with Tensors in Python, using PyTorch and TensorLy.
Home-page: https://github.com/tensorly/tensorly-torch
Author: Jean Kossaifi
Author-email: jean.kossaifi@gmail.com
License: Modified BSD
Download-URL: https://github.com/tensorly/tensorly-torch/tarball/0.5.0
Platform: UNKNOWN
Classifier: Topic :: Scientific/Engineering
Classifier: License :: OSI Approved :: BSD License
Classifier: Programming Language :: Python :: 3
License-File: LICENSE
Requires-Dist: numpy
Requires-Dist: scipy
